name_recognize/__init__.py
name_recognize/name_recognizer.py
name_recognize/names_ru.csv
name_recognize-0.1.0.dist-info/METADATA
name_recognize-0.1.0.dist-info/WHEEL
name_recognize-0.1.0.dist-info/top_level.txt
name_recognize-0.1.0.dist-info/RECORD
