Metadata-Version: 2.1
Name: name_recognize
Version: 0.1.0
Summary: Библиотека для распознавания и нормализации имен на русском языке с поддержкой нескольких стран
Author: SuperUser
Classifier: Programming Language :: Python :: 3
Classifier: License :: OSI Approved :: MIT License
Classifier: Operating System :: OS Independent
Requires-Python: >=3.6
